CHANGELOG.txt
DATASOURCE_README.md
LICENCE.txt
MANIFEST.in
README.md
README.txt
setup.py
docs/conf.py
docs/_build/html/_sources/index.rst.txt
docs/_build/html/_sources/modules.rst.txt
docs/_build/html/_sources/readme.rst.txt
docs/_build/html/_sources/readme_datasource.rst.txt
docs/_build/html/_sources/readme_pipeline.rst.txt
docs/_build/html/_sources/torch_sdk.events.rst.txt
docs/_build/html/_sources/torch_sdk.models.rst.txt
docs/_build/html/_sources/torch_sdk.rst.txt
examples/__init__.py
examples/a17_pipeline_bug_2.py
examples/a17_pipeline_bug_27_10.py
examples/airflow_cust_trans.py
examples/bank_data.py
examples/demo_sdk.py
examples/demo_sdk_2.py
examples/example_1_pipeline.py
examples/example_2_pipeline.py
examples/example_3_1_pipeline.py
examples/example_3_2_pipeline.py
examples/example_datasource_workflow.py
examples/example_datasource_workflow_2.py
examples/example_sdk.py
examples/pipeline_demo.py
examples/sso_demo.py
examples/test_gcs.py
torch_sdk/__init__.py
torch_sdk/client.py
torch_sdk/errors.py
torch_sdk/initialiser.py
torch_sdk/torch_client.py
torch_sdk/torch_http_client.py
torch_sdk.egg-info/PKG-INFO
torch_sdk.egg-info/SOURCES.txt
torch_sdk.egg-info/dependency_links.txt
torch_sdk.egg-info/requires.txt
torch_sdk.egg-info/top_level.txt
torch_sdk/events/__init__.py
torch_sdk/events/generic_event.py
torch_sdk/events/job_events.py
torch_sdk/events/log_events.py
torch_sdk/events/span_event.py
torch_sdk/models/__init__.py
torch_sdk/models/asset.py
torch_sdk/models/assetType.py
torch_sdk/models/connection.py
torch_sdk/models/create_asset.py
torch_sdk/models/datasource.py
torch_sdk/models/job.py
torch_sdk/models/notifications.py
torch_sdk/models/pipeline.py
torch_sdk/models/profile.py
torch_sdk/models/rule.py
torch_sdk/models/setting.py
torch_sdk/models/snapshot.py
torch_sdk/models/span.py
torch_sdk/models/span_context.py
torch_sdk/models/tags.py